pytest_reports/__init__.py
pytest_reports/pytest_reports.py
pytest_reports-0.0.2.dist-info/LICENSE
pytest_reports-0.0.2.dist-info/METADATA
pytest_reports-0.0.2.dist-info/WHEEL
pytest_reports-0.0.2.dist-info/RECORD
