Metadata-Version: 2.1
Name: pytest-reports
Version: 0.0.2
Summary: An interesting python package
Home-page: https://github.com/MarkHoo/pytest_reports
License: Apache-2.0
Author: Mark Hoo
Author-email: markhoo@foxmail.com
Requires-Python: >=3.7,<4.0
Classifier: Framework :: Pytest
Classifier: Intended Audience :: Developers
Classifier: Intended Audience :: Information Technology
Classifier: License :: OSI Approved :: Apache Software License
Classifier: Operating System :: MacOS
Classifier: Operating System :: Microsoft :: Windows
Classifier: Operating System :: POSIX
Classifier: Operating System :: Unix
Classifier: Programming Language :: Python :: 3
Classifier: Programming Language :: Python :: 3.7
Classifier: Programming Language :: Python :: 3.8
Classifier: Programming Language :: Python :: 3.9
Classifier: Programming Language :: Python :: 3.10
Classifier: Programming Language :: Python :: 3.11
Classifier: Programming Language :: Python :: 3 :: Only
Classifier: Programming Language :: Python :: 3.12
Classifier: Programming Language :: Python :: Implementation :: CPython
Project-URL: Bug Tracker, https://github.com/MarkHoo/pytest_reports/issues
Project-URL: Repository, https://github.com/MarkHoo/pytest_reports
